xwrpr/__init__.py
xwrpr-1.0.1.dist-info/LICENSE
xwrpr-1.0.1.dist-info/METADATA
xwrpr-1.0.1.dist-info/WHEEL
xwrpr-1.0.1.dist-info/top_level.txt
xwrpr-1.0.1.dist-info/RECORD
