Metadata-Version: 2.1
Name: xwrpr
Version: 1.0.1
Summary: This Package is deprecated. Don't use it anymore.
Author: AustrianTradingMachine
License:                     GNU GENERAL PUBLIC LICENSE
Classifier: Development Status :: 7 - Inactive
Classifier: Programming Language :: Python :: 3
Classifier: License :: OSI Approved :: GNU General Public License v3 or later (GPLv3+)
Requires-Python: <4.0,>=3.9
License-File: LICENSE
